{
  "version": "2.4.2",
  "flags": {},
  "shapes": [
    {
      "label": "蓝房顶",
      "score": 0.9873706102371216,
      "points": [
        [
          2138.530700981246,
          1934.795262978755
        ],
        [
          2142.3363557971343,
          1894.7518609469112
        ],
        [
          2098.7779538039103,
          1890.6121466892137
        ],
        [
          2094.972298988022,
          1930.6555487210576
        ]
      ],
      "group_id": null,
      "description": null,
      "difficult": false,
      "shape_type": "rotation",
      "flags": {},
      "attributes": {},
      "kie_linking": [],
      "direction": 4.80714263319573
    },
    {
      "label": "车",
      "score": 0.959888219833374,
      "points": [
        [
          2237.3851653550437,
          957.1378615948856
        ],
        [
          2245.923532721081,
          938.7312045427652
        ],
        [
          2231.0350922133157,
          931.8248459246456
        ],
        [
          2222.4967248472785,
          950.231502976766
        ]
      ],
      "group_id": null,
      "description": null,
      "difficult": false,
      "shape_type": "rotation",
      "flags": {},
      "attributes": {},
      "kie_linking": [],
      "direction": 5.146720337863805
    },
    {
      "label": "车",
      "score": 0.7608515024185181,
      "points": [
        [
          1853.0321787766043,
          569.3438332325748
        ],
        [
          1858.7983017275142,
          554.342573349941
        ],
        [
          1842.445192439216,
          548.0568320506284
        ],
        [
          1836.6790694883061,
          563.0580919332622
        ]
      ],
      "group_id": null,
      "description": null,
      "difficult": false,
      "shape_type": "rotation",
      "flags": {},
      "attributes": {},
      "kie_linking": [],
      "direction": 5.079354184861995
    },
    {
      "label": "车",
      "score": 0.4291718900203705,
      "points": [
        [
          1525.5888301048012,
          850.3136577645855
        ],
        [
          1533.2050189798551,
          829.8719108933826
        ],
        [
          1511.6912144508628,
          821.8562946279926
        ],
        [
          1504.075025575809,
          842.2980414991955
        ]
      ],
      "group_id": null,
      "description": null,
      "difficult": false,
      "shape_type": "rotation",
      "flags": {},
      "attributes": {},
      "kie_linking": [],
      "direction": 5.069036442037441
    }
  ],
  "imagePath": "keyframe_0274.jpg",
  "imageData": null,
  "imageHeight": 2160,
  "imageWidth": 3840
}