{
  "version": "2.4.2",
  "flags": {},
  "shapes": [
    {
      "label": "蓝房顶",
      "score": 0.9857738018035889,
      "points": [
        [
          2137.8218774206234,
          1932.8000250510186
        ],
        [
          2141.6666657700343,
          1893.358161093487
        ],
        [
          2099.735800802033,
          1889.2707452126533
        ],
        [
          2095.891012452622,
          1928.7126091701848
        ]
      ],
      "group_id": null,
      "description": null,
      "difficult": false,
      "shape_type": "rotation",
      "flags": {},
      "attributes": {},
      "kie_linking": [],
      "direction": 4.809561851616721
    },
    {
      "label": "车",
      "score": 0.9232626557350159,
      "points": [
        [
          2148.037989020655,
          355.1489282107636
        ],
        [
          2157.1563013093746,
          341.54218556166467
        ],
        [
          2139.21176683872,
          329.516980602713
        ],
        [
          2130.0934545500004,
          343.1237232518119
        ]
      ],
      "group_id": null,
      "description": null,
      "difficult": false,
      "shape_type": "rotation",
      "flags": {},
      "attributes": {},
      "kie_linking": [],
      "direction": 5.302786755557875
    },
    {
      "label": "车",
      "score": 0.7366334199905396,
      "points": [
        [
          2264.7535705656937,
          546.8354593109298
        ],
        [
          2274.9363093783277,
          528.6870682629642
        ],
        [
          2253.9945983796188,
          516.9370474029374
        ],
        [
          2243.811859566985,
          535.085438450903
        ]
      ],
      "group_id": null,
      "description": null,
      "difficult": false,
      "shape_type": "rotation",
      "flags": {},
      "attributes": {},
      "kie_linking": [],
      "direction": 5.22370074987016
    },
    {
      "label": "车",
      "score": 0.5078292489051819,
      "points": [
        [
          1760.5106479617023,
          577.7392960393154
        ],
        [
          1771.6980053895588,
          558.0925297912152
        ],
        [
          1756.1372249631024,
          549.2318343317784
        ],
        [
          1744.9498675352459,
          568.8786005798786
        ]
      ],
      "group_id": null,
      "description": null,
      "difficult": false,
      "shape_type": "rotation",
      "flags": {},
      "attributes": {},
      "kie_linking": [],
      "direction": 5.230023312564717
    },
    {
      "label": "车",
      "score": 0.3343941569328308,
      "points": [
        [
          2158.784018168286,
          1657.6457085211998
        ],
        [
          2169.0399698844512,
          1639.8914268044384
        ],
        [
          2148.153695454761,
          1627.8262458245033
        ],
        [
          2137.8977437385956,
          1645.5805275412647
        ]
      ],
      "group_id": null,
      "description": null,
      "difficult": false,
      "shape_type": "rotation",
      "flags": {},
      "attributes": {},
      "kie_linking": [],
      "direction": 5.236220586295935
    },
    {
      "label": "终点线",
      "score": 0.26906538009643555,
      "points": [
        [
          2076.674296539129,
          2065.1222947782003
        ],
        [
          2077.86792074955,
          1931.0582990899761
        ],
        [
          2063.8979080507147,
          1930.933918600706
        ],
        [
          2062.7042838402936,
          2064.99791428893
        ]
      ],
      "group_id": null,
      "description": null,
      "difficult": false,
      "shape_type": "rotation",
      "flags": {},
      "attributes": {},
      "kie_linking": [],
      "direction": 4.721292136419342
    }
  ],
  "imagePath": "keyframe_0065.jpg",
  "imageData": null,
  "imageHeight": 2160,
  "imageWidth": 3840
}