{
  "version": "2.4.2",
  "flags": {},
  "shapes": [
    {
      "label": "蓝房顶",
      "score": 0.980049729347229,
      "points": [
        [
          2141.641210810818,
          1934.998082858822
        ],
        [
          2145.162995587488,
          1896.4487326159767
        ],
        [
          2102.7412659958227,
          1892.5731756860998
        ],
        [
          2099.219481219153,
          1931.1225259289452
        ]
      ],
      "group_id": null,
      "description": null,
      "difficult": false,
      "shape_type": "rotation",
      "flags": {},
      "attributes": {},
      "kie_linking": [],
      "direction": 4.803493905063502
    },
    {
      "label": "车",
      "score": 0.9712554216384888,
      "points": [
        [
          1857.0757638573623,
          2006.9549951783217
        ],
        [
          1865.3614174703384,
          1986.4883456506147
        ],
        [
          1841.9234121680283,
          1976.999777770897
        ],
        [
          1833.6377585550522,
          1997.466427298604
        ]
      ],
      "group_id": null,
      "description": null,
      "difficult": false,
      "shape_type": "rotation",
      "flags": {},
      "attributes": {},
      "kie_linking": [],
      "direction": 5.097058075662476
    },
    {
      "label": "车",
      "score": 0.9481886625289917,
      "points": [
        [
          1907.6575474142362,
          2037.5304268600269
        ],
        [
          1914.0864070078394,
          2017.4581537811357
        ],
        [
          1889.8155208230685,
          2009.6845389602856
        ],
        [
          1883.3866612294653,
          2029.7568120391768
        ]
      ],
      "group_id": null,
      "description": null,
      "difficult": false,
      "shape_type": "rotation",
      "flags": {},
      "attributes": {},
      "kie_linking": [],
      "direction": 5.022350955005503
    },
    {
      "label": "车",
      "score": 0.8682540655136108,
      "points": [
        [
          1892.0246243359827,
          340.77806900311924
        ],
        [
          1899.0562684550248,
          320.1449931488941
        ],
        [
          1876.4935183642126,
          312.4557261628964
        ],
        [
          1869.4618742451705,
          333.0888020171215
        ]
      ],
      "group_id": null,
      "description": null,
      "difficult": false,
      "shape_type": "rotation",
      "flags": {},
      "attributes": {},
      "kie_linking": [],
      "direction": 5.04083971976838
    },
    {
      "label": "车",
      "score": 0.8335341811180115,
      "points": [
        [
          2552.117564811901,
          1235.428754624051
        ],
        [
          2559.5802151253115,
          1215.791060135976
        ],
        [
          2537.536976203724,
          1207.414262954074
        ],
        [
          2530.0743258903135,
          1227.051957442149
        ]
      ],
      "group_id": null,
      "description": null,
      "difficult": false,
      "shape_type": "rotation",
      "flags": {},
      "attributes": {},
      "kie_linking": [],
      "direction": 5.075550514455663
    },
    {
      "label": "车",
      "score": 0.6920161247253418,
      "points": [
        [
          1820.0972182344342,
          335.74240593168673
        ],
        [
          1828.3104436401388,
          318.98562746524743
        ],
        [
          1811.0982315946674,
          310.5491742685086
        ],
        [
          1802.8850061889627,
          327.3059527349479
        ]
      ],
      "group_id": null,
      "description": null,
      "difficult": false,
      "shape_type": "rotation",
      "flags": {},
      "attributes": {},
      "kie_linking": [],
      "direction": 5.168120312686794
    },
    {
      "label": "车",
      "score": 0.46573391556739807,
      "points": [
        [
          1637.3253660160642,
          791.2699101634679
        ],
        [
          1643.5259790415505,
          765.899328150996
        ],
        [
          1625.6658144038577,
          761.534273796493
        ],
        [
          1619.4652013783714,
          786.904855808965
        ]
      ],
      "group_id": null,
      "description": null,
      "difficult": false,
      "shape_type": "rotation",
      "flags": {},
      "attributes": {},
      "kie_linking": [],
      "direction": 4.95209174155793
    },
    {
      "label": "终点线",
      "score": 0.2810198962688446,
      "points": [
        [
          2077.220185947608,
          2063.569240833805
        ],
        [
          2078.8275138448735,
          1931.9683669801516
        ],
        [
          2064.8067915914544,
          1931.7971226915856
        ],
        [
          2063.199463694189,
          2063.397996545239
        ]
      ],
      "group_id": null,
      "description": null,
      "difficult": false,
      "shape_type": "rotation",
      "flags": {},
      "attributes": {},
      "kie_linking": [],
      "direction": 4.724602029841164
    }
  ],
  "imagePath": "keyframe_0194.jpg",
  "imageData": null,
  "imageHeight": 2160,
  "imageWidth": 3840
}