{
  "version": "2.4.2",
  "flags": {},
  "shapes": [
    {
      "label": "蓝房顶",
      "score": 0.9805760383605957,
      "points": [
        [
          2141.7607729673637,
          1932.7508519811875
        ],
        [
          2145.260765789937,
          1893.72154113381
        ],
        [
          2103.0735165834176,
          1889.9383570031875
        ],
        [
          2099.573523760844,
          1928.967667850565
        ]
      ],
      "group_id": null,
      "description": null,
      "difficult": false,
      "shape_type": "rotation",
      "flags": {},
      "attributes": {},
      "kie_linking": [],
      "direction": 4.801825757320743
    },
    {
      "label": "车",
      "score": 0.9686918258666992,
      "points": [
        [
          1784.5480716237971,
          328.0982528629888
        ],
        [
          1792.8247687861826,
          311.1498110710385
        ],
        [
          1776.4397060861638,
          303.14823761552685
        ],
        [
          1768.1630089237783,
          320.0966794074771
        ]
      ],
      "group_id": null,
      "description": null,
      "difficult": false,
      "shape_type": "rotation",
      "flags": {},
      "attributes": {},
      "kie_linking": [],
      "direction": 5.166669684644567
    },
    {
      "label": "车",
      "score": 0.9281799793243408,
      "points": [
        [
          2551.2428265699846,
          1245.1833529545352
        ],
        [
          2559.020660037676,
          1226.4505852610373
        ],
        [
          2536.89788998275,
          1217.2652249263242
        ],
        [
          2529.1200565150584,
          1235.997992619822
        ]
      ],
      "group_id": null,
      "description": null,
      "difficult": false,
      "shape_type": "rotation",
      "flags": {},
      "attributes": {},
      "kie_linking": [],
      "direction": 5.10592921375832
    },
    {
      "label": "车",
      "score": 0.8289133906364441,
      "points": [
        [
          2311.801429479891,
          1537.6749625429923
        ],
        [
          2321.122071943542,
          1517.5971177459444
        ],
        [
          2302.1945421997966,
          1508.810480572242
        ],
        [
          2292.8738997361456,
          1528.88832536929
        ]
      ],
      "group_id": null,
      "description": null,
      "difficult": false,
      "shape_type": "rotation",
      "flags": {},
      "attributes": {},
      "kie_linking": [],
      "direction": 5.147009450193272
    },
    {
      "label": "车",
      "score": 0.7975420355796814,
      "points": [
        [
          2137.4062762777835,
          397.3971874177928
        ],
        [
          2145.7101470256607,
          378.89853171607706
        ],
        [
          2122.8761639077634,
          368.64857369060564
        ],
        [
          2114.572293159886,
          387.1472293923214
        ]
      ],
      "group_id": null,
      "description": null,
      "difficult": false,
      "shape_type": "rotation",
      "flags": {},
      "attributes": {},
      "kie_linking": [],
      "direction": 5.134319859739154
    },
    {
      "label": "车",
      "score": 0.7825203537940979,
      "points": [
        [
          2309.626822798617,
          647.7245077615615
        ],
        [
          2316.837301202361,
          629.0003721051193
        ],
        [
          2296.6759726115392,
          621.2364449972275
        ],
        [
          2289.4654942077955,
          639.9605806536698
        ]
      ],
      "group_id": null,
      "description": null,
      "difficult": false,
      "shape_type": "rotation",
      "flags": {},
      "attributes": {},
      "kie_linking": [],
      "direction": 5.079976248737212
    },
    {
      "label": "车",
      "score": 0.4604398012161255,
      "points": [
        [
          2668.024385050776,
          1629.1205938584694
        ],
        [
          2675.2028818965564,
          1607.905977858623
        ],
        [
          2654.3118881425835,
          1600.8369867079368
        ],
        [
          2647.133391296803,
          1622.0516027077833
        ]
      ],
      "group_id": null,
      "description": null,
      "difficult": false,
      "shape_type": "rotation",
      "flags": {},
      "attributes": {},
      "kie_linking": [],
      "direction": 5.03867020010553
    },
    {
      "label": "终点线",
      "score": 0.277570515871048,
      "points": [
        [
          2077.556173966202,
          2063.0735057755796
        ],
        [
          2079.2600347366856,
          1933.6643463745013
        ],
        [
          2065.768105818954,
          1933.486705406061
        ],
        [
          2064.0642450484706,
          2062.8958648071393
        ]
      ],
      "group_id": null,
      "description": null,
      "difficult": false,
      "shape_type": "rotation",
      "flags": {},
      "attributes": {},
      "kie_linking": [],
      "direction": 4.725554681565386
    }
  ],
  "imagePath": "keyframe_0241.jpg",
  "imageData": null,
  "imageHeight": 2160,
  "imageWidth": 3840
}