{
  "version": "2.4.2",
  "flags": {},
  "shapes": [
    {
      "label": "蓝房顶",
      "score": 0.9862107038497925,
      "points": [
        [
          2139.3907345141347,
          1935.7244746599997
        ],
        [
          2142.861659458448,
          1895.7913017384983
        ],
        [
          2099.7128116284434,
          1892.0408756817972
        ],
        [
          2096.2418866841303,
          1931.9740486032986
        ]
      ],
      "group_id": null,
      "description": null,
      "difficult": false,
      "shape_type": "rotation",
      "flags": {},
      "attributes": {},
      "kie_linking": [],
      "direction": 4.799089419837806
    },
    {
      "label": "车",
      "score": 0.9591737389564514,
      "points": [
        [
          2626.029079052502,
          2003.707049308525
        ],
        [
          2630.762756056825,
          1984.269294288202
        ],
        [
          2610.7227825197638,
          1979.3889589922562
        ],
        [
          2605.9891055154408,
          1998.8267140125793
        ]
      ],
      "group_id": null,
      "description": null,
      "difficult": false,
      "shape_type": "rotation",
      "flags": {},
      "attributes": {},
      "kie_linking": [],
      "direction": 4.951269048448429
    },
    {
      "label": "车",
      "score": 0.7986613512039185,
      "points": [
        [
          2252.1227748023002,
          874.7701969068213
        ],
        [
          2258.6410789673137,
          855.3637561961351
        ],
        [
          2240.3094761742623,
          849.2064724047021
        ],
        [
          2233.791172009249,
          868.6129131153883
        ]
      ],
      "group_id": null,
      "description": null,
      "difficult": false,
      "shape_type": "rotation",
      "flags": {},
      "attributes": {},
      "kie_linking": [],
      "direction": 5.036432969566227
    },
    {
      "label": "车",
      "score": 0.7795513868331909,
      "points": [
        [
          1721.8559032466137,
          660.7446835362433
        ],
        [
          1729.269915339737,
          641.6578371992849
        ],
        [
          1713.7119525883472,
          635.6145693934442
        ],
        [
          1706.2979404952239,
          654.7014157304026
        ]
      ],
      "group_id": null,
      "description": null,
      "difficult": false,
      "shape_type": "rotation",
      "flags": {},
      "attributes": {},
      "kie_linking": [],
      "direction": 5.082886534925319
    },
    {
      "label": "车",
      "score": 0.6540504097938538,
      "points": [
        [
          1640.9979649632244,
          1721.2685667690016
        ],
        [
          1649.8525416450946,
          1697.9279994235098
        ],
        [
          1628.6504725367756,
          1689.8846925083421
        ],
        [
          1619.7958958549054,
          1713.225259853834
        ]
      ],
      "group_id": null,
      "description": null,
      "difficult": false,
      "shape_type": "rotation",
      "flags": {},
      "attributes": {},
      "kie_linking": [],
      "direction": 5.074980336423727
    }
  ],
  "imagePath": "keyframe_0035.jpg",
  "imageData": null,
  "imageHeight": 2160,
  "imageWidth": 3840
}