{
  "version": "2.4.2",
  "flags": {},
  "shapes": [
    {
      "label": "蓝房顶",
      "score": 0.9842767119407654,
      "points": [
        [
          2140.3544454010157,
          1933.9319981957758
        ],
        [
          2144.354015809485,
          1895.189304121853
        ],
        [
          2101.8248148528905,
          1890.7988367651617
        ],
        [
          2097.825244444421,
          1929.5415308390845
        ]
      ],
      "group_id": null,
      "description": null,
      "difficult": false,
      "shape_type": "rotation",
      "flags": {},
      "attributes": {},
      "kie_linking": [],
      "direction": 4.815258759256237
    },
    {
      "label": "车",
      "score": 0.9800369739532471,
      "points": [
        [
          2266.5764186026126,
          1588.0948456818878
        ],
        [
          2279.317217487116,
          1567.0318144867197
        ],
        [
          2262.4590733407467,
          1556.8345061247528
        ],
        [
          2249.7182744562433,
          1577.897537319921
        ]
      ],
      "group_id": null,
      "description": null,
      "difficult": false,
      "shape_type": "rotation",
      "flags": {},
      "attributes": {},
      "kie_linking": [],
      "direction": 5.256395685668809
    },
    {
      "label": "车",
      "score": 0.7388244271278381,
      "points": [
        [
          2023.6502885206553,
          962.1213838365576
        ],
        [
          2027.4147485174124,
          939.5136274429518
        ],
        [
          2010.070262016454,
          936.6255644056299
        ],
        [
          2006.305802019697,
          959.2333207992357
        ]
      ],
      "group_id": null,
      "description": null,
      "difficult": false,
      "shape_type": "rotation",
      "flags": {},
      "attributes": {},
      "kie_linking": [],
      "direction": 4.877387049790251
    },
    {
      "label": "终点线",
      "score": 0.29268041253089905,
      "points": [
        [
          2076.6256620990803,
          2063.0129939536214
        ],
        [
          2078.150716603584,
          1931.5569484918894
        ],
        [
          2064.5695588481854,
          1931.3993900795815
        ],
        [
          2063.0445043436816,
          2062.8554355413135
        ]
      ],
      "group_id": null,
      "description": null,
      "difficult": false,
      "shape_type": "rotation",
      "flags": {},
      "attributes": {},
      "kie_linking": [],
      "direction": 4.723989710394068
    }
  ],
  "imagePath": "keyframe_0265.jpg",
  "imageData": null,
  "imageHeight": 2160,
  "imageWidth": 3840
}