{
  "version": "2.4.2",
  "flags": {},
  "shapes": [
    {
      "label": "蓝房顶",
      "score": 0.9841069579124451,
      "points": [
        [
          2139.7663766634305,
          1935.8727526739474
        ],
        [
          2143.1654446994607,
          1897.3400503491355
        ],
        [
          2101.0377615201633,
          1893.6238598748807
        ],
        [
          2097.638693484133,
          1932.1565621996926
        ]
      ],
      "group_id": null,
      "description": null,
      "difficult": false,
      "shape_type": "rotation",
      "flags": {},
      "attributes": {},
      "kie_linking": [],
      "direction": 4.800373788174012
    },
    {
      "label": "车",
      "score": 0.9793493747711182,
      "points": [
        [
          2262.980418994664,
          1590.858851454912
        ],
        [
          2276.1264348404197,
          1569.739440085952
        ],
        [
          2260.2913705561173,
          1559.8827256935256
        ],
        [
          2247.1453547103615,
          1581.0021370624854
        ]
      ],
      "group_id": null,
      "description": null,
      "difficult": false,
      "shape_type": "rotation",
      "flags": {},
      "attributes": {},
      "kie_linking": [],
      "direction": 5.269160616393906
    },
    {
      "label": "车",
      "score": 0.9180439114570618,
      "points": [
        [
          1883.1705812876253,
          562.5273053208298
        ],
        [
          1888.662314055729,
          549.1996922076826
        ],
        [
          1870.0541348988982,
          541.5320666274124
        ],
        [
          1864.5624021307945,
          554.8596797405596
        ]
      ],
      "group_id": null,
      "description": null,
      "difficult": false,
      "shape_type": "rotation",
      "flags": {},
      "attributes": {},
      "kie_linking": [],
      "direction": 5.103245693441252
    },
    {
      "label": "车",
      "score": 0.7903671264648438,
      "points": [
        [
          1940.5444135837497,
          545.3544384128202
        ],
        [
          1948.925312465769,
          529.7317546525253
        ],
        [
          1931.503621084219,
          520.3857654446017
        ],
        [
          1923.1227222021998,
          536.0084492048966
        ]
      ],
      "group_id": null,
      "description": null,
      "difficult": false,
      "shape_type": "rotation",
      "flags": {},
      "attributes": {},
      "kie_linking": [],
      "direction": 5.204775112863396
    },
    {
      "label": "车",
      "score": 0.4466076195240021,
      "points": [
        [
          2025.8558428577596,
          1158.9070484487675
        ],
        [
          2030.890257391936,
          1140.9558691494635
        ],
        [
          2011.9607770152872,
          1135.6470897348263
        ],
        [
          2006.9263624811108,
          1153.5982690341302
        ]
      ],
      "group_id": null,
      "description": null,
      "difficult": false,
      "shape_type": "rotation",
      "flags": {},
      "attributes": {},
      "kie_linking": [],
      "direction": 4.985815244909153
    },
    {
      "label": "终点线",
      "score": 0.2840806841850281,
      "points": [
        [
          2076.9141939017127,
          2067.579699441514
        ],
        [
          2078.0350435314867,
          1932.8691199490718
        ],
        [
          2063.907034125631,
          1932.7515688690328
        ],
        [
          2062.786184495857,
          2067.462148361475
        ]
      ],
      "group_id": null,
      "description": null,
      "difficult": false,
      "shape_type": "rotation",
      "flags": {},
      "attributes": {},
      "kie_linking": [],
      "direction": 4.720709216031947
    }
  ],
  "imagePath": "keyframe_0269.jpg",
  "imageData": null,
  "imageHeight": 2160,
  "imageWidth": 3840
}