{
  "version": "2.4.2",
  "flags": {},
  "shapes": [
    {
      "label": "蓝房顶",
      "score": 0.9815057516098022,
      "points": [
        [
          2136.8280383218553,
          1931.8195829375852
        ],
        [
          2140.789331170774,
          1892.365570527147
        ],
        [
          2098.8898877035354,
          1888.158749581946
        ],
        [
          2094.9285948546167,
          1927.6127619923843
        ]
      ],
      "group_id": null,
      "description": null,
      "difficult": false,
      "shape_type": "rotation",
      "flags": {},
      "attributes": {},
      "kie_linking": [],
      "direction": 4.812456417079781
    },
    {
      "label": "车",
      "score": 0.9315590858459473,
      "points": [
        [
          2716.157706515753,
          1851.7850642815063
        ],
        [
          2723.393143366668,
          1830.3292905481092
        ],
        [
          2704.635292751825,
          1824.0036625251344
        ],
        [
          2697.39985590091,
          1845.4594362585315
        ]
      ],
      "group_id": null,
      "description": null,
      "difficult": false,
      "shape_type": "rotation",
      "flags": {},
      "attributes": {},
      "kie_linking": [],
      "direction": 5.037638503309133
    },
    {
      "label": "车",
      "score": 0.5781241655349731,
      "points": [
        [
          1576.8978597243613,
          798.511757211711
        ],
        [
          1581.5480923739347,
          779.34249748665
        ],
        [
          1559.6216867844278,
          774.023414297078
        ],
        [
          1554.9714541348544,
          793.192674022139
        ]
      ],
      "group_id": null,
      "description": null,
      "difficult": false,
      "shape_type": "rotation",
      "flags": {},
      "attributes": {},
      "kie_linking": [],
      "direction": 4.950379583235613
    },
    {
      "label": "车",
      "score": 0.4631877839565277,
      "points": [
        [
          2010.5235155250034,
          822.7501128845014
        ],
        [
          2017.6872398132477,
          804.3980883439309
        ],
        [
          2000.045179543356,
          797.5114990539752
        ],
        [
          1992.8814552551116,
          815.8635235945457
        ]
      ],
      "group_id": null,
      "description": null,
      "difficult": false,
      "shape_type": "rotation",
      "flags": {},
      "attributes": {},
      "kie_linking": [],
      "direction": 5.0845493555029355
    },
    {
      "label": "车",
      "score": 0.2635692358016968,
      "points": [
        [
          1978.6706399689444,
          640.0340763240639
        ],
        [
          1986.0086093786501,
          618.5584627337236
        ],
        [
          1963.863387130665,
          610.9916957706627
        ],
        [
          1956.5254177209592,
          632.467309361003
        ]
      ],
      "group_id": null,
      "description": null,
      "difficult": false,
      "shape_type": "rotation",
      "flags": {},
      "attributes": {},
      "kie_linking": [],
      "direction": 5.041640210147727
    }
  ],
  "imagePath": "keyframe_0323.jpg",
  "imageData": null,
  "imageHeight": 2160,
  "imageWidth": 3840
}